{
	"sn": "facebook",
	"login": "5584986849516",
	"password": "perfilururai022",
	"status": 2,
	"id": "100089893186233",
	"name": "",
	"amountFriends": "",
	"screenname": "Ana Santos",
	"birthdate": "2005 January 23",
	"country": "",
	"isAvatarExists": false,
	"cookie": [
		{
			"domain": ".facebook.com",
			"expirationDate": 1680110829,
			"hostOnly": false,
			"httpOnly": false,
			"name": "dpr",
			"path": "/",
			"sameSite": "no_restriction",
			"secure": true,
			"session": false,
			"storeId": "0",
			"value": "1.25"
		},
		{
			"domain": ".facebook.com",
			"expirationDate": 1714065380.695688,
			"hostOnly": false,
			"httpOnly": true,
			"name": "sb",
			"path": "/",
			"sameSite": "no_restriction",
			"secure": true,
			"session": false,
			"storeId": "0",
			"value": "rDcbZLLj4mXf4-WKBp9RFS4q"
		},
		{
			"domain": ".facebook.com",
			"expirationDate": 1714065325.21154,
			"hostOnly": false,
			"httpOnly": true,
			"name": "datr",
			"path": "/",
			"sameSite": "no_restriction",
			"secure": true,
			"session": false,
			"storeId": "0",
			"value": "rDcbZFgcvEfFNaPZD-jyMUGx"
		},
		{
			"domain": ".facebook.com",
			"expirationDate": 1680110180.695596,
			"hostOnly": false,
			"httpOnly": false,
			"name": "locale",
			"path": "/",
			"sameSite": "no_restriction",
			"secure": true,
			"session": false,
			"storeId": "0",
			"value": "pt_BR"
		},
		{
			"domain": ".facebook.com",
			"expirationDate": 1711041374.695723,
			"hostOnly": false,
			"httpOnly": false,
			"name": "c_user",
			"path": "/",
			"sameSite": "no_restriction",
			"secure": true,
			"session": false,
			"storeId": "0",
			"value": "100089893186233"
		},
		{
			"domain": ".facebook.com",
			"expirationDate": 1711041374.695753,
			"hostOnly": false,
			"httpOnly": true,
			"name": "xs",
			"path": "/",
			"sameSite": "no_restriction",
			"secure": true,
			"session": false,
			"storeId": "0",
			"value": "36%3AtwyLn_J-1dEQUg%3A2%3A1679505380%3A-1%3A-1"
		},
		{
			"domain": ".facebook.com",
			"expirationDate": 1687281905.133203,
			"hostOnly": false,
			"httpOnly": true,
			"name": "fr",
			"path": "/",
			"sameSite": "no_restriction",
			"secure": true,
			"session": false,
			"storeId": "0",
			"value": "0Ob7hLmtGDRviRQPr.AWVxa1HInGSX6hqqPgnTb9Huw8s.BkGzes.4E.AAA.0.0.BkGzny.AWXJx2b0jnQ"
		},
		{
			"domain": ".facebook.com",
			"expirationDate": 1680110829,
			"hostOnly": false,
			"httpOnly": false,
			"name": "wd",
			"path": "/",
			"sameSite": "lax",
			"secure": true,
			"session": false,
			"storeId": "0",
			"value": "736x654"
		},
		{
			"domain": ".facebook.com",
			"hostOnly": false,
			"httpOnly": false,
			"name": "presence",
			"path": "/",
			"sameSite": "unspecified",
			"secure": true,
			"session": true,
			"storeId": "0",
			"value": "C%7B%22t3%22%3A%5B%5D%2C%22utc3%22%3A1679505984707%2C%22v%22%3A1%7D"
		}
	],
	"lastEventDate": "22.03.2023 17:43 Registro",
	"code2fa": "OE5CCKUS2EK45CFGDLYGGEPRYOPBGE3N",
	"recoveryCodes": [
		"01856056",
		"06714997",
		"07620249",
		"13894140",
		"38520598",
		"48368395",
		"50953721",
		"54695253",
		"83271228",
		"84824941"
	]
}